tabulk/__init__.py
tabulk/_version.py
tabulk/utils.py
tabulk/db/__init__.py
tabulk/db/maria.py
tabulk/db/mysql.py
tabulk/db/postgresql.py
tabulk/db/sqlite.py
tabulk/db/sqlserver.py
tabulk/db/sqlutils/postgresql.sql
tabulk-0.0.0.dist-info/licenses/LICENSE.txt
tabulk-0.0.0.dist-info/METADATA
tabulk-0.0.0.dist-info/WHEEL
tabulk-0.0.0.dist-info/entry_points.txt
tabulk-0.0.0.dist-info/top_level.txt
tabulk-0.0.0.dist-info/RECORD
